{"interfaceLanguages":{"swift":[{"children":[{"title":"Classes","type":"groupMarker"},{"children":[{"title":"Instance Methods","type":"groupMarker"},{"path":"\/documentation\/weatherapp\/appdelegate\/application(_:configurationforconnecting:options:)","title":"func application(UIApplication, configurationForConnecting: UISceneSession, options: UIScene.ConnectionOptions) -> UISceneConfiguration","type":"method"},{"path":"\/documentation\/weatherapp\/appdelegate\/application(_:diddiscardscenesessions:)","title":"func application(UIApplication, didDiscardSceneSessions: Set<UISceneSession>)","type":"method"},{"path":"\/documentation\/weatherapp\/appdelegate\/application(_:didfinishlaunchingwithoptions:)","title":"func application(UIApplication, didFinishLaunchingWithOptions: [UIApplication.LaunchOptionsKey : Any]?) -> Bool","type":"method"},{"title":"Default Implementations","type":"groupMarker"},{"children":[{"title":"Type Methods","type":"groupMarker"},{"path":"\/documentation\/weatherapp\/appdelegate\/main()","title":"static func main()","type":"method"}],"path":"\/documentation\/weatherapp\/appdelegate\/uiapplicationdelegate-implementations","title":"UIApplicationDelegate Implementations","type":"symbol"}],"path":"\/documentation\/weatherapp\/appdelegate","title":"AppDelegate","type":"class"},{"children":[{"title":"Type Properties","type":"groupMarker"},{"path":"\/documentation\/weatherapp\/dklog\/mode-swift.type.property","title":"static var mode: Mode","type":"property"},{"title":"Type Methods","type":"groupMarker"},{"path":"\/documentation\/weatherapp\/dklog\/log(_:separator:terminator:filename:line:function:type:mode:)","title":"static func log(Any..., separator: String, terminator: String, fileName: String, line: Int, function: String, type: LogType, mode: Mode)","type":"method"},{"title":"Enumerations","type":"groupMarker"},{"children":[{"title":"Enumeration Cases","type":"groupMarker"},{"path":"\/documentation\/weatherapp\/dklog\/logtype\/error","title":"case error","type":"case"},{"path":"\/documentation\/weatherapp\/dklog\/logtype\/info","title":"case info","type":"case"},{"path":"\/documentation\/weatherapp\/dklog\/logtype\/normal","title":"case normal","type":"case"},{"path":"\/documentation\/weatherapp\/dklog\/logtype\/success","title":"case success","type":"case"},{"path":"\/documentation\/weatherapp\/dklog\/logtype\/warning","title":"case warning","type":"case"},{"title":"Initializers","type":"groupMarker"},{"path":"\/documentation\/weatherapp\/dklog\/logtype\/init(rawvalue:)","title":"init?(rawValue: Int)","type":"init"},{"title":"Instance Properties","type":"groupMarker"},{"path":"\/documentation\/weatherapp\/dklog\/logtype\/name","title":"var name: String","type":"property"},{"title":"Default Implementations","type":"groupMarker"},{"children":[{"title":"Operators","type":"groupMarker"},{"path":"\/documentation\/weatherapp\/dklog\/logtype\/!=(_:_:)","title":"static func != (Self, Self) -> Bool","type":"op"}],"path":"\/documentation\/weatherapp\/dklog\/logtype\/equatable-implementations","title":"Equatable Implementations","type":"symbol"},{"children":[{"title":"Instance Properties","type":"groupMarker"},{"path":"\/documentation\/weatherapp\/dklog\/logtype\/hashvalue","title":"var hashValue: Int","type":"property"},{"title":"Instance Methods","type":"groupMarker"},{"path":"\/documentation\/weatherapp\/dklog\/logtype\/hash(into:)","title":"func hash(into: inout Hasher)","type":"method"}],"path":"\/documentation\/weatherapp\/dklog\/logtype\/rawrepresentable-implementations","title":"RawRepresentable Implementations","type":"symbol"}],"path":"\/documentation\/weatherapp\/dklog\/logtype","title":"DKLog.LogType","type":"enum"},{"children":[{"title":"Enumeration Cases","type":"groupMarker"},{"path":"\/documentation\/weatherapp\/dklog\/mode-swift.enum\/debug","title":"case debug","type":"case"},{"path":"\/documentation\/weatherapp\/dklog\/mode-swift.enum\/release","title":"case release","type":"case"},{"title":"Initializers","type":"groupMarker"},{"path":"\/documentation\/weatherapp\/dklog\/mode-swift.enum\/init(rawvalue:)","title":"init?(rawValue: String)","type":"init"},{"title":"Default Implementations","type":"groupMarker"},{"children":[{"title":"Operators","type":"groupMarker"},{"path":"\/documentation\/weatherapp\/dklog\/mode-swift.enum\/!=(_:_:)","title":"static func != (Self, Self) -> Bool","type":"op"}],"path":"\/documentation\/weatherapp\/dklog\/mode-swift.enum\/equatable-implementations","title":"Equatable Implementations","type":"symbol"},{"children":[{"title":"Instance Properties","type":"groupMarker"},{"path":"\/documentation\/weatherapp\/dklog\/mode-swift.enum\/hashvalue","title":"var hashValue: Int","type":"property"},{"title":"Instance Methods","type":"groupMarker"},{"path":"\/documentation\/weatherapp\/dklog\/mode-swift.enum\/hash(into:)","title":"func hash(into: inout Hasher)","type":"method"}],"path":"\/documentation\/weatherapp\/dklog\/mode-swift.enum\/rawrepresentable-implementations","title":"RawRepresentable Implementations","type":"symbol"}],"path":"\/documentation\/weatherapp\/dklog\/mode-swift.enum","title":"DKLog.Mode","type":"enum"}],"path":"\/documentation\/weatherapp\/dklog","title":"DKLog","type":"class"},{"children":[{"title":"Instance Properties","type":"groupMarker"},{"path":"\/documentation\/weatherapp\/scenedelegate\/window","title":"var window: UIWindow?","type":"property"},{"title":"Instance Methods","type":"groupMarker"},{"path":"\/documentation\/weatherapp\/scenedelegate\/scene(_:willconnectto:options:)","title":"func scene(UIScene, willConnectTo: UISceneSession, options: UIScene.ConnectionOptions)","type":"method"},{"path":"\/documentation\/weatherapp\/scenedelegate\/scenedidbecomeactive(_:)","title":"func sceneDidBecomeActive(UIScene)","type":"method"},{"path":"\/documentation\/weatherapp\/scenedelegate\/scenediddisconnect(_:)","title":"func sceneDidDisconnect(UIScene)","type":"method"},{"path":"\/documentation\/weatherapp\/scenedelegate\/scenedidenterbackground(_:)","title":"func sceneDidEnterBackground(UIScene)","type":"method"},{"path":"\/documentation\/weatherapp\/scenedelegate\/scenewillenterforeground(_:)","title":"func sceneWillEnterForeground(UIScene)","type":"method"},{"path":"\/documentation\/weatherapp\/scenedelegate\/scenewillresignactive(_:)","title":"func sceneWillResignActive(UIScene)","type":"method"}],"path":"\/documentation\/weatherapp\/scenedelegate","title":"SceneDelegate","type":"class"},{"children":[{"title":"Instance Properties","type":"groupMarker"},{"path":"\/documentation\/weatherapp\/viewcontroller\/weatherservice","title":"let weatherService: WeatherService","type":"property"},{"title":"Instance Methods","type":"groupMarker"},{"path":"\/documentation\/weatherapp\/viewcontroller\/onclicksubmit(_:)","title":"func onClickSubmit(UIButton)","type":"method"},{"path":"\/documentation\/weatherapp\/viewcontroller\/viewdidload()","title":"func viewDidLoad()","type":"method"}],"path":"\/documentation\/weatherapp\/viewcontroller","title":"ViewController","type":"class"},{"title":"Variables","type":"groupMarker"},{"path":"\/documentation\/weatherapp\/weatherapikey","title":"let WeatherAPIKey: String","type":"var"}],"path":"\/documentation\/weatherapp","title":"WeatherApp","type":"module"}]},"schemaVersion":{"major":0,"minor":1,"patch":0}}